mfutil/__init__.py
mfutil/bash_wrapper.py
mfutil/cli.py
mfutil/eval.py
mfutil/exc.py
mfutil/jinja2_extensions.py
mfutil/misc.py
mfutil/net.py
mfutil/cli_tools/__init__.py
mfutil/cli_tools/get_domainname.py
mfutil/cli_tools/get_full_hostname.py
mfutil/cli_tools/get_ip_for_hostname.py
mfutil/cli_tools/get_real_ip.py
mfutil/cli_tools/get_simple_hostname.py
mfutil/cli_tools/mfprogress.py
mfutil/cli_tools/ping_tcp_port.py
mfutil/cli_tools/recursive_kill.py
mfutil-0.3.2.dist-info/licenses/LICENSE
tests/__init__.py
tests/test_cli.py
tests/test_core.py
tests/test_eval.py
tests/test_net.py
mfutil-0.3.2.dist-info/METADATA
mfutil-0.3.2.dist-info/WHEEL
mfutil-0.3.2.dist-info/entry_points.txt
mfutil-0.3.2.dist-info/top_level.txt
mfutil-0.3.2.dist-info/RECORD
