Metadata-Version: 2.4
Name: mfutil
Version: 0.3.2
Home-page: https://github.com/metwork-framework/mfutil
Requires-Python: >=3.8
License-File: LICENSE
Requires-Dist: six
Requires-Dist: jinja2
Requires-Dist: bash
Requires-Dist: psutil
Requires-Dist: inotify_simple
Requires-Dist: netifaces2
Requires-Dist: rich>=1.2.3
Requires-Dist: simpleeval>=0.9.13
Requires-Dist: inotify_simple
Dynamic: home-page
Dynamic: license-file
Dynamic: requires-dist
Dynamic: requires-python
